agenttoolprotocol-0.2.5.dist-info/licenses/LICENSE
atp_sdk/__init__.py
atp_sdk/clients.py
atp_ui/__init__.py
atp_ui/components.py
atp_ui/contents.py
atp_ui/forms.py
atp_ui/layouts.py
atp_ui/utils.py
django_atp/__init__.py
django_atp/admin.py
django_atp/apps.py
django_atp/models.py
django_atp/registry.py
django_atp/tests.py
django_atp/urls.py
django_atp/views.py
django_atp/management/commands/run_toolkit_polling.py
django_atp/migrations/__init__.py
fastapi_atp/registry.py
flask_atp/registry.py
agenttoolprotocol-0.2.5.dist-info/METADATA
agenttoolprotocol-0.2.5.dist-info/WHEEL
agenttoolprotocol-0.2.5.dist-info/top_level.txt
agenttoolprotocol-0.2.5.dist-info/RECORD
