Metadata-Version: 2.4
Name: AgentToolProtocol
Version: 0.2.5
Summary: A ChatATP Python SDK for registering, exposing, and serving your own Python functions as tools via the ATP platform. Supports secure OAuth2 flows, dynamic tool registration, and real-time tool invocation via WebSocket or HTTP.
Author-email: Samuel Obinna Chimdi <sammyfirst6@gmail.com>
License: MIT
Project-URL: Homepage, https://github.com/agent-tool-protocol/python-sdk
Project-URL: Repository, https://github.com/agent-tool-protocol/python-sdk
Project-URL: Issues,  https://github.com/agent-tool-protocol/python-sdk/issues
Project-URL: Documentation, https://github.com/agent-tool-protocol/python-sdk/blob/main/README.md
Keywords: agent,toolkit,chat,sdk,llm,ChatATP,ChatGPT,AI Agent Frameworks,websocket,http,api,tools,functions,automation,ATP,Agent Tool Protocol,ATP SDK,tool registration,tool invocation,tool serving,toolkit registration,toolkit invocation,toolkit serving,remote tool invocation,remote tool serving,remote tool registration,remote toolkit invocation,Samuel Obinna Chimdi,ChatATP Agent
Classifier: Development Status :: 4 - Beta
Classifier: Intended Audience :: Developers
Classifier: License :: OSI Approved :: MIT License
Classifier: Programming Language :: Python :: 3.7
Classifier: Programming Language :: Python :: 3.8
Classifier: Programming Language :: Python :: 3.9
Classifier: Programming Language :: Python :: 3.10
Classifier: Programming Language :: Python :: 3.11
Classifier: Programming Language :: Python :: 3.12
Classifier: Operating System :: OS Independent
Classifier: Topic :: Software Development :: Libraries :: Python Modules
Classifier: Topic :: Scientific/Engineering :: Artificial Intelligence
Classifier: Topic :: Internet :: WWW/HTTP
Classifier: Topic :: Communications :: Chat
Classifier: Topic :: Software Development :: Libraries :: Application Frameworks
Requires-Python: >=3.7
License-File: LICENSE
Requires-Dist: requests>=2.31.0
Requires-Dist: websocket-client>=1.6.1
Dynamic: license-file
